luminalai/__init__.py
luminalai-0.1.0.dist-info/METADATA
luminalai-0.1.0.dist-info/WHEEL
luminalai-0.1.0.dist-info/top_level.txt
luminalai-0.1.0.dist-info/RECORD
